aa_gen/__init__.py
aa_gen/main.py
aa_gen/fonts/OFL.txt
aa_gen/fonts/Poppins-Black.ttf
aa_gen/fonts/Poppins-BlackItalic.ttf
aa_gen/fonts/Poppins-Bold.ttf
aa_gen/fonts/Poppins-BoldItalic.ttf
aa_gen/fonts/Poppins-ExtraBold.ttf
aa_gen/fonts/Poppins-ExtraBoldItalic.ttf
aa_gen/fonts/Poppins-ExtraLight.ttf
aa_gen/fonts/Poppins-ExtraLightItalic.ttf
aa_gen/fonts/Poppins-Italic.ttf
aa_gen/fonts/Poppins-Light.ttf
aa_gen/fonts/Poppins-LightItalic.ttf
aa_gen/fonts/Poppins-Medium.ttf
aa_gen/fonts/Poppins-MediumItalic.ttf
aa_gen/fonts/Poppins-Regular.ttf
aa_gen/fonts/Poppins-SemiBold.ttf
aa_gen/fonts/Poppins-SemiBoldItalic.ttf
aa_gen/fonts/Poppins-Thin.ttf
aa_gen/fonts/Poppins-ThinItalic.ttf
aa_gen/fonts/__init__.py
aa_gen-0.0.13.dist-info/LICENSE
aa_gen-0.0.13.dist-info/METADATA
aa_gen-0.0.13.dist-info/WHEEL
aa_gen-0.0.13.dist-info/entry_points.txt
aa_gen-0.0.13.dist-info/top_level.txt
aa_gen-0.0.13.dist-info/RECORD
