Metadata-Version: 2.1
Name: aa-gen
Version: 0.0.13
Summary: A simple ascii art generator
Home-page: UNKNOWN
Author: kobayashi1757
Author-email: kobayashi1757@gmail.com
License: UNKNOWN
Platform: UNKNOWN
Classifier: Programming Language :: Python :: 3
Classifier: License :: OSI Approved :: MIT License
Classifier: Operating System :: OS Independent
Requires-Python: >=3.7
Requires-Dist: appdirs (>=1.4.4numpy>=1.18.4)
Requires-Dist: Pillow (>=7.1.2)
